pecos/__init__.py
pecos/types.py
pecos/version.py
pecos/check_circuits/__init__.py
pecos/check_circuits/checks2circuit.py
pecos/circuit_converters/__init__.py
pecos/circuit_converters/std2chs.py
pecos/circuit_runners/__init__.py
pecos/circuit_runners/standard.py
pecos/circuit_runners/timing_runner.py
pecos/circuits/__init__.py
pecos/circuits/circuit.py
pecos/circuits/circuit_new.py
pecos/circuits/logical_circuit.py
pecos/circuits/quantum_circuit.py
pecos/circuits/quantum_circuit_new.py
pecos/decoders/__init__.py
pecos/decoders/dummy_decoder/__init__.py
pecos/decoders/dummy_decoder/dummy_decoder.py
pecos/decoders/mwpm2d/__init__.py
pecos/decoders/mwpm2d/mwpm2d.py
pecos/decoders/mwpm2d/precomputing.py
pecos/error_gens/__init__.py
pecos/error_gens/class_errors_circuit.py
pecos/error_gens/depolar_gen.py
pecos/error_gens/gatewise_gen.py
pecos/error_gens/parent_class_error_gen.py
pecos/error_gens/xerror_gen.py
pecos/error_gens/xzerror_gen.py
pecos/error_gens/zerror_gen.py
pecos/misc/__init__.py
pecos/misc/commute.py
pecos/misc/errors.py
pecos/misc/stabilizer_funcs.py
pecos/misc/std_ouput.py
pecos/misc/symbol_library.py
pecos/misc/threshold_curve.py
pecos/qeccs/__init__.py
pecos/qeccs/gate_parent_class.py
pecos/qeccs/helper_functions.py
pecos/qeccs/instruction_parent_class.py
pecos/qeccs/plot.py
pecos/qeccs/qecc_parent_class.py
pecos/qeccs/color_488/__init__.py
pecos/qeccs/color_488/circuit_implementation1.py
pecos/qeccs/color_488/color_488.py
pecos/qeccs/color_488/gates.py
pecos/qeccs/color_488/instructions.py
pecos/qeccs/surface_4444/__init__.py
pecos/qeccs/surface_4444/gates.py
pecos/qeccs/surface_4444/instructions.py
pecos/qeccs/surface_4444/surface_4444.py
pecos/qeccs/surface_medial_4444/__init__.py
pecos/qeccs/surface_medial_4444/gates.py
pecos/qeccs/surface_medial_4444/instructions.py
pecos/qeccs/surface_medial_4444/surface_medial_4444.py
pecos/simulators/__init__.py
pecos/simulators/_parent_sim_classes.py
pecos/simulators/compile_cython.py
quantum_pecos-0.2.0.dist-info/LICENSE
quantum_pecos-0.2.0.dist-info/METADATA
quantum_pecos-0.2.0.dist-info/WHEEL
quantum_pecos-0.2.0.dist-info/top_level.txt
quantum_pecos-0.2.0.dist-info/RECORD
