Metadata-Version: 2.1
Name: quantum-pecos
Version: 0.2.0
Summary: PECOS (Performance Estimator of Codes On Surfaces) is a package designed to facilitate the evaluation and study of quantum error correcting codes.
Home-page: https://github.com/PECOS-packages/PECOS
Author: Ciarán Ryan-Anderson
Author-email: ciaran@pecos.io
License: Apache 2
Classifier: Programming Language :: Python :: 3.6
Classifier: Programming Language :: Python :: 3.7
Classifier: License :: OSI Approved :: Apache Software License
Classifier: Operating System :: OS Independent
Requires-Python: >=3.6
License-File: LICENSE
Requires-Dist: numpy <2.0,>=1.15.0
Requires-Dist: scipy <2.0,>=1.1.0
Requires-Dist: matplotlib <4.0,>=2.2.0
Requires-Dist: networkx <3.0,>=2.1.0
Requires-Dist: sortedcontainers <3.0,>=2.0.0
Provides-Extra: all
Requires-Dist: quantum-pecos[simulators] ; extra == 'all'
Provides-Extra: simulators
Requires-Dist: cython ; extra == 'simulators'
Requires-Dist: projectq ; extra == 'simulators'
